ml_automated_123/__init__.py
ml_automated_123/package.py
ml_automated_123/factories/Factory.py
ml_automated_123/factories/__init__.py
ml_automated_123/metrics/__init__.py
ml_automated_123/metrics/accuracy.py
ml_automated_123/metrics/f1.py
ml_automated_123/metrics/precision.py
ml_automated_123/metrics/r2.py
ml_automated_123/metrics/recall.py
ml_automated_123/models/Model.py
ml_automated_123/models/__init__.py
ml_automated_123/models/classification/ClassificationModel.py
ml_automated_123/models/classification/LogisticRegression.py
ml_automated_123/models/classification/RandomForest.py
ml_automated_123/models/classification/XGBoost.py
ml_automated_123/models/classification/__init__.py
ml_automated_123/models/regression/RandomForest.py
ml_automated_123/models/regression/RegressionModel.py
ml_automated_123/models/regression/XGBoost.py
ml_automated_123/models/regression/__init__.py
ml_automated_123/preprocessing/Parser.py
ml_automated_123/preprocessing/Scaler.py
ml_automated_123/preprocessing/__init__.py
ml_automated_123/readers/__init__.py
ml_automated_123/readers/csv_reader.py
ml_automated_123/task_type/Task.py
ml_automated_123/task_type/__init__.py
ml_automated_123-1.0.dist-info/LICENSE.txt.txt
ml_automated_123-1.0.dist-info/METADATA
ml_automated_123-1.0.dist-info/WHEEL
ml_automated_123-1.0.dist-info/top_level.txt
ml_automated_123-1.0.dist-info/RECORD
