Metadata-Version: 2.1
Name: ml-automated-123
Version: 1.0
Summary: Automated machine learning
Home-page: https://github.com/noahweber1/ml_automated_123
Author: Noah Weber
Author-email: noahweber53@ygmail.com
License: UNKNOWN
Download-URL: https://github.com/noahweber1/ml_automated_123
Keywords: Auto_ML
Platform: UNKNOWN
Classifier: Development Status :: 4 - Beta
Classifier: Intended Audience :: Developers
Classifier: Programming Language :: Python :: 3
Classifier: Topic :: Scientific/Engineering
Classifier: Topic :: Scientific/Engineering :: Mathematics
Classifier: Topic :: Scientific/Engineering :: Artificial Intelligence
Requires-Dist: hyperopt (>=0.2)
Requires-Dist: networkx (>=2.1)
Requires-Dist: numpy (>=1.17)
Requires-Dist: pandas (>=0.24)
Requires-Dist: scikit-learn (>=0.22)
Requires-Dist: xgboost (>=0.9)
